titania_nlp_project/titania_nlp_project.py
titania_nlp_project-0.1.2.dist-info/METADATA
titania_nlp_project-0.1.2.dist-info/WHEEL
titania_nlp_project-0.1.2.dist-info/top_level.txt
titania_nlp_project-0.1.2.dist-info/RECORD
