Metadata-Version: 2.1
Name: titania-nlp-project
Version: 0.1.2
Summary: Named Entity Recognition package using SpaCy
Home-page: https://github.com/your_username/titania_nlp_project
Author: Sai Teja Reddy
Author-email: saitejareddy123@gmail.com
License: UNKNOWN
Platform: UNKNOWN
Requires-Python: >=3.6, <4
Requires-Dist: spacy (<4.0.0,>=3.0.0)
Requires-Dist: spacytextblob (>=3.0.1)
Requires-Dist: nltk (>=3.6.0)
Requires-Dist: boto3 (<2.0.0,>=1.17.71)
Requires-Dist: transformers (>=4.8.1)
Requires-Dist: torch (>=1.7.0)
